jsonable/__init__.py
jsonable/functions.py
jsonable/instance.py
jsonable/jsonable.py
jsonable/self_constructor.py
jsonable/type.py
jsonable/tests/__init__.py
jsonable/tests/test_functions.py
jsonable/tests/test_instance.py
jsonable/tests/test_jsonable.py
jsonable/tests/test_self_constructor.py
jsonable/tests/test_type.py
jsonable-0.3.1.dist-info/DESCRIPTION.rst
jsonable-0.3.1.dist-info/METADATA
jsonable-0.3.1.dist-info/RECORD
jsonable-0.3.1.dist-info/WHEEL
jsonable-0.3.1.dist-info/metadata.json
jsonable-0.3.1.dist-info/top_level.txt
