Metadata-Version: 2.0
Name: jsonable
Version: 0.3.1
Summary: An abstract class that supports jsonserialization/deserialization.
Home-page: https://github.com/halfak/JSONable-data-types
Author: Aaron Halfaker
Author-email: ahalfaker@wikimedia.org
License: MIT
Platform: UNKNOWN
Classifier: Development Status :: 4 - Beta
Classifier: Programming Language :: Python
Classifier: Programming Language :: Python :: 3
Classifier: Environment :: Other Environment
Classifier: Intended Audience :: Developers
Classifier: License :: OSI Approved :: MIT License
Classifier: Operating System :: OS Independent
Classifier: Topic :: Software Development :: Libraries :: Python Modules
